JSONLibGem/2.py
JSONLibGem/__init__.py
JSONLibGem/main.py
JSONLibGem-0.0.4.dist-info/METADATA
JSONLibGem-0.0.4.dist-info/WHEEL
JSONLibGem-0.0.4.dist-info/top_level.txt
JSONLibGem-0.0.4.dist-info/RECORD
