Metadata-Version: 2.1
Name: JSONLibGem
Version: 0.0.4
Summary: This is the simplest module for serializing and deserializing json.
Home-page: 
Author: Gemion
Author-email: ms.m4x@yandex.ru
Keywords: json
Classifier: Programming Language :: Python :: 3.12
Classifier: License :: OSI Approved :: MIT License
Classifier: Operating System :: OS Independent
Requires-Python: >=3.6
